{"version":1,"resource":"file:///home/invictus/.config/waybar/config.jsonc","entries":[{"id":"wLQy.jsonc","timestamp":1750966206411},{"id":"0ZPX.jsonc","timestamp":1750966744845},{"id":"INDD.jsonc","timestamp":1750966774093},{"id":"NW2o.jsonc","timestamp":1750966789342},{"id":"omBd.jsonc","timestamp":1750966801818},{"id":"OmSa.jsonc","timestamp":1750966888762},{"id":"WFni.jsonc","timestamp":1750966926625},{"id":"xsoX.jsonc","timestamp":1750966943843},{"id":"Sgm6.jsonc","timestamp":1750967000241},{"id":"HSwr.jsonc","timestamp":1750967299827},{"id":"Tt4Z.jsonc","timestamp":1750967343167},{"id":"tZEH.jsonc","timestamp":1750967372825},{"id":"xG8t.jsonc","timestamp":1750967401993},{"id":"b4de.jsonc","timestamp":1750967427655},{"id":"zqB1.jsonc","source":"undoRedo.source","timestamp":1750967435862},{"id":"Erun.jsonc","timestamp":1750986446327},{"id":"LhU5.jsonc","timestamp":1751631541421},{"id":"JYcb.jsonc","timestamp":1751631557652},{"id":"GQAp.jsonc","source":"undoRedo.source","timestamp":1751631560289},{"id":"vibc.jsonc","timestamp":1751631618154},{"id":"b7EV.jsonc","source":"undoRedo.source","timestamp":1751631662541},{"id":"YHHR.jsonc","timestamp":1751631673779},{"id":"7aBA.jsonc","source":"undoRedo.source","timestamp":1751631689023}]}